{"countryCode": "SK", "country": "Slovakia", "count": 29, "people": [{"name": "Pavol Babjak", "id": "35131"}, {"name": "Petra Barboríková", "id": "186385"}, {"name": "Kristína Bihariová", "id": "128325"}, {"name": "Mária Brešťanská", "id": "200597"}, {"name": "Zuzana Briešková", "id": "153055"}, {"name": "Monika Brillova", "id": "233093"}, {"name": "Denisa Chovancova", "id": "148548"}, {"name": "Anton Cunderlik", "id": "32326"}, {"name": "Jana Dečková", "id": "326116"}, {"name": "Erik Dosedla", "id": "61000"}, {"name": "Dávid Galo", "id": "320130"}, {"name": "Martin Harčár", "id": "240839"}, {"name": "Ivan Janco", "id": "229673"}, {"name": "Tatiana Janegova", "id": "209835"}, {"name": "Martin Juhas", "id": "101165"}, {"name": "Oľga Káčeriková", "id": "61924"}, {"name": "Eva Kornanova", "id": "125357"}, {"name": "Stefan Kozuskanic", "id": "62754"}, {"name": "Maria Kubalova", "id": "272136"}, {"name": "Viliam Martinček", "id": "242581"}, {"name": "Michaela Martišová", "id": "160100"}, {"name": "Hana Neštiak Habánová", "id": "303047"}, {"name": "Lucia Rákošová", "id": "122607"}, {"name": "Michal Semivan", "id": "138646"}, {"name": "Katarína Skalová", "id": "162774"}, {"name": "Petra Tallova", "id": "178299"}, {"name": "Gonosová Tomová", "id": "231138"}, {"name": "Petra Turnova", "id": "192953"}, {"name": "Ľuboš Zelizňák", "id": "302906"}]}