{"countryCode": "BG", "country": "Bulgaria", "count": 19, "people": [{"name": "Vangeliya Atanasova", "id": "87496"}, {"name": "Anna Bogdanova", "id": "95079"}, {"name": "Petya Chaveeva", "id": "79513"}, {"name": "Ivelina Dimitrova", "id": "148878"}, {"name": "Dejana Dojchinovska", "id": "129060"}, {"name": "Slavyana Galeva", "id": "103099"}, {"name": "Elitsa Gyokova", "id": "171048"}, {"name": "Ivan Ivanov", "id": "61538"}, {"name": "Milena Manuelyan", "id": "107939"}, {"name": "Tsvetomira Markova", "id": "85257"}, {"name": "Jeni Panaiotova", "id": "82532"}, {"name": "Gabriela Panayotova", "id": "199215"}, {"name": "Ivanka Peychinova", "id": "120060"}, {"name": "Boris Stoilov", "id": "100777"}, {"name": "Violeta Stratieva", "id": "50213"}, {"name": "Tsvetoslav Vassilev", "id": "151551"}, {"name": "Maria Yankova", "id": "36381"}, {"name": "Hristo Yordanov", "id": "163136"}, {"name": "Krasimira Zhelyazkova", "id": "82020"}]}