{"countryCode": "TN", "country": "Tunisia", "count": 12, "people": [{"name": "Raja Azri", "id": "240566"}, {"name": "Asma Ben Aicha", "id": "123168"}, {"name": "Sonia Ben Hamouda", "id": "146515"}, {"name": "Farah Benghachame", "id": "146780"}, {"name": "Ghassen Boulahia", "id": "206650"}, {"name": "Aref Driss", "id": "106625"}, {"name": "Maher Ftouh", "id": "106362"}, {"name": "Ben Ammar Kais", "id": "132169"}, {"name": "Zied Kamoun", "id": "95659"}, {"name": "Mohamed Oussama Khelifi", "id": "222584"}, {"name": "Kallel Mazen", "id": "64517"}, {"name": "Boujemaa Oueslati", "id": "22225"}]}