{"countryCode": "CO", "country": "Colombia", "count": 83, "people": [{"name": "Isabel Acosta", "id": "61063"}, {"name": "German Adarme Mayorga", "id": "157263"}, {"name": "Walter Annicchiarico", "id": "226636"}, {"name": "Fabian Andres Aragon", "id": "169425"}, {"name": "Rafael Leonardo Aragon Mendoza", "id": "176343"}, {"name": "Gilberto Arcila", "id": "93616"}, {"name": "Edgar Arenas", "id": "73796"}, {"name": "Astrid Ayus", "id": "129697"}, {"name": "Daniel Bautista", "id": "237049"}, {"name": "Luis Beltran", "id": "147145"}, {"name": "Jesús Andres Benavides Serralde", "id": "46134"}, {"name": "Luis Botero", "id": "53033"}, {"name": "Henry Andres Botia Rodriguez", "id": "106577"}, {"name": "Andres Camacho", "id": "83593"}, {"name": "Natalia Cardozo Buitrago", "id": "154381"}, {"name": "Christian Carreño", "id": "125312"}, {"name": "Pedro Charris", "id": "136092"}, {"name": "Carlos Andrés Contreras Gutiérrez De Piñeres", "id": "63470"}, {"name": "Jairo Diaz", "id": "98620"}, {"name": "Dr Diego Hernando Diaz Botero", "id": "84862"}, {"name": "Carlos Jaime Echeverry Ciro", "id": "62379"}, {"name": "Alba Esquivel Villabona", "id": "45469"}, {"name": "Hugo Fernandez", "id": "212625"}, {"name": "Ariel Florido", "id": "88139"}, {"name": "Raisa Fragozo Villero", "id": "218173"}, {"name": "Calle Francisco", "id": "246829"}, {"name": "Dahiana Gallo", "id": "103829"}, {"name": "Wilmar Garcia Sacipa", "id": "87419"}, {"name": "Eliana Maritza García Villamizar", "id": "136853"}, {"name": "Samuel Gelvez Tellez", "id": "101598"}, {"name": "Jessica Giraldo Echeverri", "id": "302188"}, {"name": "Ivan Enrique Gomez", "id": "74726"}, {"name": "Luisa Fernanda Gómez López", "id": "76618"}, {"name": "Liseth Vanessa Gonzalez", "id": "251321"}, {"name": "Pablo Gonzalez", "id": "173055"}, {"name": "Ricardo Gonzalez", "id": "120913"}, {"name": "Viviana Andrea Gonzalez Carrillo", "id": "109587"}, {"name": "Sandra Gutierrez", "id": "105076"}, {"name": "Wilson Eberto Guzman Castro", "id": "206999"}, {"name": "Diana Hoyos", "id": "241032"}, {"name": "Claudia Hoyos Aguirre", "id": "132803"}, {"name": "John Jairo Jaramillo Prado", "id": "68301"}, {"name": "Quintero Guevara Jarol Augusto", "id": "91252"}, {"name": "Garrido Gutierrez Jesus David", "id": "115107"}, {"name": "Muhammed Ali Jimenez Farak", "id": "202303"}, {"name": "David Fortunato Juan Sierra", "id": "225973"}, {"name": "Oscar Lavalle", "id": "131806"}, {"name": "Carlos David Lozano Z", "id": "42635"}, {"name": "Yuly Andrea Marquez Castañeda", "id": "232498"}, {"name": "Jessica Martinez", "id": "229479"}, {"name": "Angy Meneses", "id": "226727"}, {"name": "Alejandro Muñoz Vargas", "id": "233484"}, {"name": "Paula Andrea Oliveros-orozco", "id": "93111"}, {"name": "Juan Otero", "id": "35495"}, {"name": "Armando Ovalle-bracho", "id": "160304"}, {"name": "Rodrigo Palma Bernal", "id": "133082"}, {"name": "Rafael Adolfo Parra Lesmes", "id": "86412"}, {"name": "Andrea Pazos Sandoval", "id": "137371"}, {"name": "Isabel Cristina Perdomo Loaiza", "id": "236728"}, {"name": "Monica Pinilla", "id": "203639"}, {"name": "David Stivel Pinzon Garcia", "id": "162417"}, {"name": "Richard Prasca De La Hoz", "id": "151291"}, {"name": "Javier Andres Ramirez Martinez", "id": "78227"}, {"name": "Estefania Ramirez Naranjo", "id": "214587"}, {"name": "Nadia Ramirez Perez", "id": "156710"}, {"name": "Juan Carlos Ramírez Villa", "id": "67799"}, {"name": "Francisco Javier Reales Najera", "id": "272960"}, {"name": "Guillermo Ivan Reyes Clavijo", "id": "73567"}, {"name": "Luis Eduardo Reyes Lara", "id": "85484"}, {"name": "Ruben Rodriguez", "id": "71313"}, {"name": "Andres Felipe Rojas Borda", "id": "261362"}, {"name": "Ximena Carolina Romero Infante", "id": "25191"}, {"name": "Daniel Ronderos Dumit", "id": "12303"}, {"name": "Pedro Rozo Reina", "id": "195739"}, {"name": "Natalia Sanchez Bocanegra", "id": "163988"}, {"name": "Jaime Serrato", "id": "64653"}, {"name": "Oscar Armando Suarez Cepeda", "id": "78835"}, {"name": "Katerin Cristina Torres Berra", "id": "196999"}, {"name": "Camilo Triana", "id": "208889"}, {"name": "Carla Usta", "id": "213076"}, {"name": "Catalina Valencia", "id": "46181"}, {"name": "Gabriela Marisol Vallejo Bastidas", "id": "100116"}, {"name": "Pablo Victoria", "id": "69723"}]}