{"countryCode": "PL", "country": "Poland", "count": 202, "people": [{"name": "Beata Adrianowicz", "id": "252424"}, {"name": "Urszula Ajdacka-matczuk", "id": "155292"}, {"name": "Świetlicki Aleksy", "id": "279574"}, {"name": "Jakub Andrzejewski", "id": "115029"}, {"name": "Jarosław Bal", "id": "66568"}, {"name": "Tomasz Banet", "id": "86866"}, {"name": "Kinga Bańkowska", "id": "314432"}, {"name": "Piotr Barcikowski", "id": "78941"}, {"name": "Martyna Bednorz", "id": "213919"}, {"name": "Mateusz Biedrycki", "id": "292154"}, {"name": "Karol Bielasik", "id": "66979"}, {"name": "Krzysztof Bielicki", "id": "78674"}, {"name": "Marek Bilar", "id": "69875"}, {"name": "Sara Borkowska", "id": "330084"}, {"name": "Daniel Boroń", "id": "245881"}, {"name": "Aleksandra Boryn-gajek", "id": "102350"}, {"name": "Robert Brawura-biskupski-samaha", "id": "78413"}, {"name": "Michał Budzik", "id": "228263"}, {"name": "Katarzyna Bukato", "id": "226066"}, {"name": "Dariusz Burek", "id": "148856"}, {"name": "Tomasz Błasiak", "id": "122084"}, {"name": "Jakub Chmielewski", "id": "226560"}, {"name": "Michał Chojnacki", "id": "66307"}, {"name": "Wojciech Chróściel", "id": "126916"}, {"name": "Michał Ciebiera", "id": "135968"}, {"name": "Agnieszka Czapska", "id": "280933"}, {"name": "Piotr Dawid", "id": "61708"}, {"name": "Marzena Debska", "id": "67150"}, {"name": "Jakub Dobroch", "id": "275568"}, {"name": "Jakub Tomasz Doruchowski", "id": "126041"}, {"name": "Magdalena Drąg", "id": "274091"}, {"name": "Mariusz Dubiel", "id": "19911"}, {"name": "Miłosz Dymon", "id": "172604"}, {"name": "Piotr Dziergawko", "id": "117693"}, {"name": "Joanna Elias", "id": "61500"}, {"name": "Michał Filip", "id": "234583"}, {"name": "Dagmara Filipecka-tyczka", "id": "85570"}, {"name": "Magdalena Fiolna", "id": "123051"}, {"name": "Wojciech Flis", "id": "272324"}, {"name": "Marta Florea", "id": "119659"}, {"name": "Janina Fryze", "id": "101417"}, {"name": "Anna Gąsiorowska", "id": "97748"}, {"name": "Joanna Gaweł", "id": "77358"}, {"name": "Rafael Gniadek", "id": "66652"}, {"name": "Tomasz Góra", "id": "123599"}, {"name": "Ewa Gostkowska", "id": "167637"}, {"name": "Anna Grybos", "id": "99272"}, {"name": "Adam Grzeczka", "id": "153168"}, {"name": "Aleksandra Gładych-macioszek", "id": "310297"}, {"name": "Joanna Głowska-ciemny", "id": "120484"}, {"name": "Anita Hamela-olkowska", "id": "32301"}, {"name": "Piotr Hincz", "id": "105020"}, {"name": "Oleksiy Holdobin", "id": "150580"}, {"name": "Joanna Hołody-zaręba", "id": "95249"}, {"name": "Dominika Hudziak", "id": "78543"}, {"name": "Rafal Iciek", "id": "66648"}, {"name": "Tomasz Jachymski", "id": "132323"}, {"name": "Gizela Jagielska", "id": "63755"}, {"name": "Lukasz Jagielski", "id": "78201"}, {"name": "Aleksandra Jagodzińska", "id": "234166"}, {"name": "Katarzyna Jalinik", "id": "42612"}, {"name": "Michal Jaszczur", "id": "121098"}, {"name": "Karol Kamiński", "id": "293498"}, {"name": "Małgorzata Kania", "id": "108185"}, {"name": "Katarzyna Karwasik- Kajszczarek", "id": "115648"}, {"name": "Kamil Kiełbasiński", "id": "145274"}, {"name": "Andrzej Kisiel", "id": "177289"}, {"name": "Christopher Kobierzycki", "id": "183583"}, {"name": "Ewelina Koch", "id": "98598"}, {"name": "Jakub Kociuba", "id": "162901"}, {"name": "Rafal Kocylowski", "id": "43750"}, {"name": "Adrianna Kondracka", "id": "99186"}, {"name": "Andrzej Korniluk", "id": "75770"}, {"name": "Stanislav Korobkin", "id": "274330"}, {"name": "Przemyslaw Kosinski", "id": "76670"}, {"name": "Joanna Kowalczyk", "id": "275844"}, {"name": "Malgorzata Kowalska", "id": "110761"}, {"name": "Radoslaw Kozaryn", "id": "188349"}, {"name": "Marek Kozarzewski", "id": "63068"}, {"name": "Karolina Krajewska", "id": "110469"}, {"name": "Aleksandra Krokocka", "id": "141550"}, {"name": "Mateusz Kryczka", "id": "245238"}, {"name": "Joanna Krygowska-zielińska", "id": "86602"}, {"name": "Waldemar Krzeszowski", "id": "104132"}, {"name": "Antoni Kubiak", "id": "76146"}, {"name": "Waldemar Kucharczuk", "id": "138460"}, {"name": "Joanna Kuran-ohde", "id": "65309"}, {"name": "Dorota Kurdzielewicz", "id": "160763"}, {"name": "Maksymilian Kurkowski", "id": "155745"}, {"name": "Agata Kuszerska", "id": "121017"}, {"name": "Slawomir Kuzniak", "id": "130917"}, {"name": "Magdalena Kłosowska - Kwapisz", "id": "78844"}, {"name": "Slawomir Laber", "id": "77726"}, {"name": "Mateusz Lepiarczyk", "id": "115499"}, {"name": "Ewa Letkiewicz", "id": "87262"}, {"name": "Marcin Lewandowski", "id": "129772"}, {"name": "Ewelina Lewkowicz", "id": "294036"}, {"name": "Magdalena Litwinska", "id": "107535"}, {"name": "Ewelina Litwińska-korcz", "id": "106894"}, {"name": "Paulina Machura", "id": "190790"}, {"name": "Marek Maslak", "id": "80603"}, {"name": "Diana Massalska", "id": "91185"}, {"name": "Magdalena Massalska-wolska", "id": "210290"}, {"name": "Maciej Mazurec", "id": "75941"}, {"name": "Stanisław Andrzej Michalak", "id": "145524"}, {"name": "Michał Michalski", "id": "93549"}, {"name": "Marian Migda", "id": "42930"}, {"name": "Michal Migda", "id": "81466"}, {"name": "Paweł Mikulski", "id": "136965"}, {"name": "Karolina Mitruczuk", "id": "277323"}, {"name": "Andrzej Miturski", "id": "115361"}, {"name": "Katarzyna Mlodzianowska-kosel", "id": "53145"}, {"name": "Robert Murawski", "id": "151803"}, {"name": "Julia Murlewska", "id": "107455"}, {"name": "Konrad Muzykiewicz", "id": "94484"}, {"name": "Agnieszka Nocun", "id": "47933"}, {"name": "Urszula Nowacka", "id": "153343"}, {"name": "Agnieszka Nowak", "id": "121844"}, {"name": "Patrycja Nowak - Florek", "id": "76214"}, {"name": "Krzysztof Nowosielski", "id": "73532"}, {"name": "Marcin Nylec", "id": "117461"}, {"name": "Rafał Oleszczuk", "id": "310350"}, {"name": "Kamila Orzechowska", "id": "294871"}, {"name": "Maciej Orzechowski", "id": "124202"}, {"name": "Katarzyna Osowska", "id": "283679"}, {"name": "Karolina Panek-laszczyńska", "id": "132285"}, {"name": "Maciej Pankau", "id": "75147"}, {"name": "Andrzej Pasieczny", "id": "116698"}, {"name": "Agata Pawłosek", "id": "201560"}, {"name": "Bartlomiej Pflaum", "id": "95841"}, {"name": "Mariola Piekarska", "id": "304981"}, {"name": "Bartosz Pietrzycki", "id": "67957"}, {"name": "Kamil Pluta", "id": "172817"}, {"name": "Sandra Radzicka-mularczyk", "id": "137530"}, {"name": "Magdalena Rajtar", "id": "265943"}, {"name": "Grzegorz Rak", "id": "237193"}, {"name": "Beata Rebizant", "id": "171693"}, {"name": "Marta Robenek", "id": "157830"}, {"name": "Witold Rogiewicz", "id": "77543"}, {"name": "Wioletta Rozmus-warcholińska", "id": "43810"}, {"name": "Magda Rybak-krzyszkowska", "id": "77102"}, {"name": "Jakub Rzepka", "id": "105891"}, {"name": "Marek Sajewicz", "id": "78721"}, {"name": "Ismaiel Salloum", "id": "131149"}, {"name": "Yevheniia Sankova", "id": "315375"}, {"name": "Anna Scholz", "id": "61179"}, {"name": "Krzysztof Siemionek", "id": "331216"}, {"name": "Antoni Sierant", "id": "74010"}, {"name": "Mateusz Sikorski", "id": "140466"}, {"name": "Katarzyna Skibińska", "id": "231923"}, {"name": "Artur Skowyra", "id": "144194"}, {"name": "Małgorzata Smyk", "id": "158298"}, {"name": "Magdalena Smyka", "id": "141062"}, {"name": "Maciej W Socha", "id": "76773"}, {"name": "Nicole Sochacki-wójcicka", "id": "85581"}, {"name": "Piotr Sołowiej", "id": "74564"}, {"name": "Roman Spyra", "id": "130233"}, {"name": "Jakub Staniczek", "id": "141480"}, {"name": "Paweł Stanirowski", "id": "129295"}, {"name": "Mateusz Stępień", "id": "240328"}, {"name": "Zbigniew Studziński", "id": "72189"}, {"name": "Aleksandra Stupak", "id": "116492"}, {"name": "Dariusz Swatowski", "id": "93361"}, {"name": "Mateusz Świątkowski", "id": "155961"}, {"name": "Piotr Świderczak", "id": "174682"}, {"name": "Oskar Sylwestrzak", "id": "190232"}, {"name": "Przemysław Szadok", "id": "150412"}, {"name": "Anna Szczepkowska", "id": "233324"}, {"name": "Paweł Szczerba", "id": "135899"}, {"name": "Rafal Szpak", "id": "119612"}, {"name": "Krzysztof Szpejankowski", "id": "83110"}, {"name": "Agata Szpera", "id": "103818"}, {"name": "Monika Szpotanska", "id": "126780"}, {"name": "Marcin Szymański", "id": "139101"}, {"name": "Grzegorz Szymczak", "id": "107281"}, {"name": "Adrian Tekieli-pawłowski", "id": "241209"}, {"name": "Jakub Toczek", "id": "245501"}, {"name": "Agnieszka Tomasińska", "id": "159606"}, {"name": "Anna Totko-świętoń", "id": "82617"}, {"name": "Przemysław Ustianowski", "id": "85491"}, {"name": "Piotr Wegrzyn", "id": "19989"}, {"name": "Jacek Więcek", "id": "80388"}, {"name": "Marcin Wiechec", "id": "43120"}, {"name": "Witold Wiesiołek", "id": "95463"}, {"name": "Roland Wilk", "id": "121556"}, {"name": "Karolina Wisniewska", "id": "243209"}, {"name": "Sławomir Wójtewicz", "id": "74866"}, {"name": "Dominik Wójtowicz", "id": "106936"}, {"name": "Cezary Wojtyła", "id": "126764"}, {"name": "Daniel Wolder", "id": "111205"}, {"name": "Bartłomiej Wolski", "id": "76565"}, {"name": "Piotr Włodarski", "id": "77183"}, {"name": "Przemyslaw Zajaczkowski", "id": "77556"}, {"name": "Maciej Zalewski", "id": "85644"}, {"name": "Dariusz Zarotynski", "id": "43188"}, {"name": "Mateusz Zborowski", "id": "101282"}, {"name": "Malgorzata Zielinska", "id": "134436"}, {"name": "Tomasz Zielinski", "id": "53129"}, {"name": "Magdalena Zietara", "id": "203220"}, {"name": "Andrzej Zmaczyński", "id": "77788"}, {"name": "Anna Zmelonek-znamirowska", "id": "63371"}, {"name": "Jakub Źrebiec", "id": "165201"}]}